stripe_payment_setup/__init__.py
stripe_payment_setup/app.py
stripe_payment_setup/settings.py
stripe_payment_setup-0.1.1.dist-info/entry_points.txt
stripe_payment_setup-0.1.1.dist-info/WHEEL
stripe_payment_setup-0.1.1.dist-info/METADATA
stripe_payment_setup-0.1.1.dist-info/RECORD
